a2a_server/__init__.py
a2a_server/__main__.py
a2a_server/agent_card.py
a2a_server/app.py
a2a_server/arguments.py
a2a_server/config.py
a2a_server/deduplication.py
a2a_server/handlers_setup.py
a2a_server/logging.py
a2a_server/main.py
a2a_server/methods.py
a2a_server/metrics.py
a2a_server/pubsub.py
a2a_server/run.py
a2a_server/session_store_factory.py
a2a_server/middleware/__init__.py
a2a_server/middleware/auth.py
a2a_server/middleware/rate_limit.py
a2a_server/routes/__init__.py
a2a_server/routes/debug.py
a2a_server/routes/handlers.py
a2a_server/routes/health.py
a2a_server/routes/session_export.py
a2a_server/routes/session_routes.py
a2a_server/sample_agents/__init__.py
a2a_server/sample_agents/chef_agent.py
a2a_server/sample_agents/chuk_chef.py
a2a_server/sample_agents/chuk_pirate.py
a2a_server/sample_agents/chuk_researcher.py
a2a_server/sample_agents/perplexity_agent.py
a2a_server/sample_agents/pirate_agent.py
a2a_server/sample_agents/time_agent.py
a2a_server/sample_agents/weather_agent.py
a2a_server/security/__init__.py
a2a_server/security/auth.py
a2a_server/session/__init__.py
a2a_server/session/analytics.py
a2a_server/session/lifecycle.py
a2a_server/session/manager.py
a2a_server/session/models.py
a2a_server/tasks/__init__.py
a2a_server/tasks/discovery.py
a2a_server/tasks/task_handler_registry.py
a2a_server/tasks/task_manager.py
a2a_server/tasks/handlers/__init__.py
a2a_server/tasks/handlers/echo_handler.py
a2a_server/tasks/handlers/pirate_vision_handler.py
a2a_server/tasks/handlers/resilient_handler.py
a2a_server/tasks/handlers/session_aware_task_handler.py
a2a_server/tasks/handlers/task_handler.py
a2a_server/tasks/handlers/time_ticker_handler.py
a2a_server/tasks/handlers/adk/__init__.py
a2a_server/tasks/handlers/adk/adk_agent_adapter.py
a2a_server/tasks/handlers/adk/google_adk_handler.py
a2a_server/tasks/handlers/adk/google_adk_protocol.py
a2a_server/tasks/handlers/chuk/__init__.py
a2a_server/tasks/handlers/chuk/chuk_agent.py
a2a_server-0.6.1.dist-info/METADATA
a2a_server-0.6.1.dist-info/WHEEL
a2a_server-0.6.1.dist-info/entry_points.txt
a2a_server-0.6.1.dist-info/top_level.txt
a2a_server-0.6.1.dist-info/RECORD
