Metadata-Version: 2.4
Name: a2a-server
Version: 0.6.1
Summary: In-memory FSM for the A2A Protocol with Pydantic v2 models
Requires-Python: >=3.11
Requires-Dist: a2a-json-rpc>=0.3
Requires-Dist: asyncio>=3.4.3
Requires-Dist: pydantic>=2.11.3
Requires-Dist: fastapi>=0.115.12
Requires-Dist: uvicorn>=0.34.1
Requires-Dist: httpx>=0.28.1
Requires-Dist: pyyaml>=6.0.2
Requires-Dist: google-adk>=0.2.0
Requires-Dist: litellm>=1.66.3
Requires-Dist: python-json-logger>=3.3.0
Requires-Dist: prometheus-client>=0.22.0
Requires-Dist: opentelemetry-sdk>=1.32.1
Requires-Dist: opentelemetry-exporter-otlp>=1.33.1
Requires-Dist: opentelemetry-exporter-prometheus>=0.54b1
Requires-Dist: aiofiles>=24.1.0
Requires-Dist: chuk-ai-session-manager>=0.7.1
Requires-Dist: httptools>=0.6.4
Requires-Dist: chuk-llm>=0.8.13
Requires-Dist: chuk-tool-processor>=0.6.4
Provides-Extra: dev
Requires-Dist: pytest>=7.0.0; extra == "dev"
Requires-Dist: pytest-asyncio>=0.20.0; extra == "dev"
